openbiomcp/__init__.py
openbiomcp/main.py
openbiomcp/modules/cutadapt/__init__.py
openbiomcp/modules/cutadapt/cutadapt.py
openbiomcp/modules/fastqc/__init__.py
openbiomcp/modules/fastqc/fastqc.py
openbiomcp/modules/multiqc/__init__.py
openbiomcp/modules/multiqc/multiqc.py
openbiomcp/modules/searching_file/__init__.py
openbiomcp/modules/searching_file/searching_file.py
openbiomcp/modules/star_alignment/__init__.py
openbiomcp/modules/star_alignment/star_alignment.py
openbiomcp/modules/trim_galore/__init__.py
openbiomcp/modules/trim_galore/trim_galore.py
openbiomcp-0.1.1.dist-info/METADATA
openbiomcp-0.1.1.dist-info/WHEEL
openbiomcp-0.1.1.dist-info/entry_points.txt
openbiomcp-0.1.1.dist-info/top_level.txt
openbiomcp-0.1.1.dist-info/RECORD
