Metadata-Version: 2.4
Name: openbiomcp
Version: 0.1.1
Summary: BioOpenMCP: Model Context Protocol tools and CLI for bioinformatics workflows.
Requires-Python: >=3.8
Requires-Dist: mcp[cli]>=1.10.1
